{
  "hash": "bf5b9e9b",
  "configHash": "eb756917",
  "lockfileHash": "d0489108",
  "browserHash": "8c9a954b",
  "optimized": {
    "react/jsx-dev-runtime": {
      "src": "../../node_modules/react/jsx-dev-runtime.js",
      "file": "react_jsx-dev-runtime.js",
      "fileHash": "20102461",
      "needsInterop": true
    },
    "react": {
      "src": "../../node_modules/react/index.js",
      "file": "react.js",
      "fileHash": "4ed7d75f",
      "needsInterop": true
    },
    "react-dom/client": {
      "src": "../../node_modules/react-dom/client.js",
      "file": "react-dom_client.js",
      "fileHash": "92a99873",
      "needsInterop": true
    },
    "@react-three/fiber": {
      "src": "../../node_modules/@react-three/fiber/dist/react-three-fiber.esm.js",
      "file": "@react-three_fiber.js",
      "fileHash": "1a25ea6d",
      "needsInterop": false
    },
    "firebase/app": {
      "src": "../../node_modules/firebase/app/dist/esm/index.esm.js",
      "file": "firebase_app.js",
      "fileHash": "971a19db",
      "needsInterop": false
    },
    "firebase/analytics": {
      "src": "../../node_modules/firebase/analytics/dist/esm/index.esm.js",
      "file": "firebase_analytics.js",
      "fileHash": "681a2b61",
      "needsInterop": false
    },
    "firebase/auth": {
      "src": "../../node_modules/firebase/auth/dist/esm/index.esm.js",
      "file": "firebase_auth.js",
      "fileHash": "31219274",
      "needsInterop": false
    },
    "three": {
      "src": "../../node_modules/three/build/three.module.js",
      "file": "three.js",
      "fileHash": "0c4aca36",
      "needsInterop": false
    },
    "framer-motion": {
      "src": "../../node_modules/framer-motion/dist/es/index.mjs",
      "file": "framer-motion.js",
      "fileHash": "2204bd60",
      "needsInterop": false
    },
    "axios": {
      "src": "../../node_modules/axios/index.js",
      "file": "axios.js",
      "fileHash": "e7bc2e7e",
      "needsInterop": false
    },
    "@stripe/react-stripe-js": {
      "src": "../../node_modules/@stripe/react-stripe-js/dist/react-stripe.esm.mjs",
      "file": "@stripe_react-stripe-js.js",
      "fileHash": "ef46bb60",
      "needsInterop": false
    },
    "@stripe/stripe-js": {
      "src": "../../node_modules/@stripe/stripe-js/lib/index.mjs",
      "file": "@stripe_stripe-js.js",
      "fileHash": "365df02a",
      "needsInterop": false
    },
    "@react-three/drei": {
      "src": "../../node_modules/@react-three/drei/index.js",
      "file": "@react-three_drei.js",
      "fileHash": "3eac49c7",
      "needsInterop": false
    }
  },
  "chunks": {
    "hls-R7NYNUNI": {
      "file": "hls-R7NYNUNI.js"
    },
    "chunk-T2F7LD4Q": {
      "file": "chunk-T2F7LD4Q.js"
    },
    "vision_bundle-3QUMERFG": {
      "file": "vision_bundle-3QUMERFG.js"
    },
    "chunk-CU73NCLI": {
      "file": "chunk-CU73NCLI.js"
    },
    "chunk-2JQ33WOL": {
      "file": "chunk-2JQ33WOL.js"
    },
    "chunk-SGVWXKAT": {
      "file": "chunk-SGVWXKAT.js"
    },
    "chunk-7RFQQ6AE": {
      "file": "chunk-7RFQQ6AE.js"
    },
    "chunk-2GK3IQSO": {
      "file": "chunk-2GK3IQSO.js"
    },
    "chunk-AE6BCOJN": {
      "file": "chunk-AE6BCOJN.js"
    },
    "chunk-P2WWKT7D": {
      "file": "chunk-P2WWKT7D.js"
    },
    "chunk-G3PMV62Z": {
      "file": "chunk-G3PMV62Z.js"
    }
  }
}